ansible_specdoc/__init__.py
ansible_specdoc/cli.py
ansible_specdoc/objects.py
ansible_specdoc-0.0.18.dist-info/LICENSE
ansible_specdoc-0.0.18.dist-info/METADATA
ansible_specdoc-0.0.18.dist-info/WHEEL
ansible_specdoc-0.0.18.dist-info/entry_points.txt
ansible_specdoc-0.0.18.dist-info/top_level.txt
ansible_specdoc-0.0.18.dist-info/RECORD
