Metadata-Version: 2.2
Name: ansible-specdoc
Version: 0.0.18
Summary: A simple tool for generating Ansible collection documentation from module spec.
Home-page: https://github.com/linode/ansible-specdoc/
Author: Linode
Author-email: dev-dx@linode.com
License: Apache License 2.0
Keywords: ansible
Requires-Python: >=3.9
License-File: LICENSE
Requires-Dist: PyYAML>=6.0.1
Requires-Dist: Jinja2>=3.0.1
Requires-Dist: redbaron>=0.9.2
Dynamic: author
Dynamic: author-email
Dynamic: description
Dynamic: description-content-type
Dynamic: home-page
Dynamic: keywords
Dynamic: license
Dynamic: requires-dist
Dynamic: requires-python
Dynamic: summary
